pyncer/__init__.py
pyncer/text/__init__.py
pyncer/text/data.py
pyncer/text/model.py
pyncer/text/util.py
pyncer-0.0.1.dist-info/METADATA
pyncer-0.0.1.dist-info/WHEEL
pyncer-0.0.1.dist-info/license
pyncer-0.0.1.dist-info/top_level.txt
pyncer-0.0.1.dist-info/RECORD
