Metadata-Version: 2.1
Name: pyncer
Version: 0.0.1
Summary: yet a captcha library
Home-page: https://github.com/chenshenchao/pyncer
Author: chenshenchao
Author-email: chenshenchao@outlook.com
License: MIT
Keywords: pyncer captcha
Platform: any
Classifier: License :: OSI Approved :: MIT License
Classifier: Intended Audience :: Developers
Classifier: Operating System :: OS Independent
Classifier: Programming Language :: Python :: 3
Classifier: Programming Language :: Python :: 3.7
Classifier: Programming Language :: Python :: 3.8
Classifier: Programming Language :: Python :: 3.9
Requires-Dist: ran (>=0.0.5)
Requires-Dist: numpy (>=1.21.1)
Requires-Dist: pillow (>=8.3.1)
Requires-Dist: torch (>=1.9.0)
Requires-Dist: torchvision (>=0.10.0)
Requires-Dist: torchaudio (>=0.9.0)
Requires-Dist: torchnet (>=0.0.4)
